{"title":"Narcos.S02E07.WEB.X264-DEFLATE","uid":15734707,"size":605614702,"categoryP":"video","categoryS":"tv_shows","magnet":"?xt=urn:btih:093c974d459ee96b0e6da8a814db4fe6efabaef1&amp;dn=Narcos.S02E07.WEB.X264-DEFLATE&amp;tr=udp%3A%2F%2Ftracker.leechers-paradise.org%3A6969&amp;tr=udp%3A%2F%2Fzer0day.ch%3A1337&amp;tr=udp%3A%2F%2Fopen.demonii.com%3A1337&amp;tr=udp%3A%2F%2Ftracker.coppersurfer.tk%3A6969&amp;tr=udp%3A%2F%2Fexodus.desync.com%3A6969","seeders":1,"leechers":0,"uploader":"TvTeam","files":4,"time":1472824554,"description":"Torrent from:\r\n~~~~~~~~~~~~ \nhttps://www.torrenting.com\r\n\r\nJoin us and become part of the BIG family! Yarrrrrrrrrrrrrr!!!","torrent":{"xt":"urn:btih:093c974d459ee96b0e6da8a814db4fe6efabaef1","amp;dn":"Narcos.S02E07.WEB.X264-DEFLATE","amp;tr":["udp%3A%2F%2Ftracker.leechers-paradise.org%3A6969","udp%3A%2F%2Fzer0day.ch%3A1337","udp%3A%2F%2Fopen.demonii.com%3A1337","udp%3A%2F%2Ftracker.coppersurfer.tk%3A6969","udp%3A%2F%2Fexodus.desync.com%3A6969"],"infoHash":"093c974d459ee96b0e6da8a814db4fe6efabaef1","infoHashBuffer":{"type":"Buffer","data":[9,60,151,77,69,158,233,107,14,109,168,168,20,219,79,230,239,171,174,241]},"announce":[],"urlList":[]}}