{"title":"Archer 2009 S05E10 720p HDTV x264","uid":9910446,"size":233926050,"categoryP":"video","categoryS":"hd___tv_shows","magnet":"?xt=urn:btih:0a18d14c639cefc6c79ac957b38b6e41465f4906&amp;dn=Archer+2009+S05E10+720p+HDTV+x264&amp;tr=udp%3A%2F%2Ftracker.openbittorrent.com%3A80&amp;tr=udp%3A%2F%2Fopen.demonii.com%3A1337&amp;tr=udp%3A%2F%2Ftracker.coppersurfer.tk%3A6969&amp;tr=udp%3A%2F%2Fexodus.desync.com%3A6969","seeders":1,"leechers":1,"uploader":"oftiscroft","files":-1,"time":1396886965,"description":"\nAt ISIS, an international spy agency, global crises are merely opportunities for its highly trained employees to confuse, undermine, betray and royally screw each other.\n\nSeason 5, Episode 10\n\nVideo\nFormat/Info                              : Advanced Video Codec\nDuration                                 : 20mn 23s\nBit rate                                 : 1 179 Kbps\nWidth                                    : 1 280 pixels\nHeight                                   : 720 pixels\nDisplay aspect ratio                     : 16:9\nFrame rate                               : 23.976 fps\nWriting library                          : x264 core 138 r2358 9e941d1\n\n\nAudio\nFormat                                   : AC-3\nBit rate                                 : 320 Kbps\nChannel(s)                               : 6 channels\nChannel positions                        : Front: L C R, Side: L R, LFE\nSampling rate                            : 48.0 KHz\nBit depth                                : 16 bits\nCompression mode                         : Lossy","torrent":{"xt":"urn:btih:0a18d14c639cefc6c79ac957b38b6e41465f4906","amp;dn":"Archer+2009+S05E10+720p+HDTV+x264","amp;tr":["udp%3A%2F%2Ftracker.openbittorrent.com%3A80","udp%3A%2F%2Fopen.demonii.com%3A1337","udp%3A%2F%2Ftracker.coppersurfer.tk%3A6969","udp%3A%2F%2Fexodus.desync.com%3A6969"],"infoHash":"0a18d14c639cefc6c79ac957b38b6e41465f4906","infoHashBuffer":{"type":"Buffer","data":[10,24,209,76,99,156,239,198,199,154,201,87,179,139,110,65,70,95,73,6]},"announce":[],"urlList":[]}}