{"title":"Ivy Manor 3 - Tropical Submission (BDSM Latex &amp; Bondage) mpg","uid":3299756,"size":624154950,"categoryP":"porn","categoryS":"movies","magnet":"?xt=urn:btih:0d2fee67d5908d71f1c9276a2f108b40b612438d&amp;dn=Ivy+Manor+3+-+Tropical+Submission+%28BDSM+Latex+%26+Bondage%29+mpg&amp;tr=udp%3A%2F%2Ftracker.openbittorrent.com%3A80&amp;tr=udp%3A%2F%2Fopen.demonii.com%3A1337&amp;tr=udp%3A%2F%2Ftracker.coppersurfer.tk%3A6969&amp;tr=udp%3A%2F%2Fexodus.desync.com%3A6969","seeders":1,"leechers":0,"uploader":"Quinty_Jones","files":1,"time":1110318735,"description":"Enjoy","torrent":{"xt":"urn:btih:0d2fee67d5908d71f1c9276a2f108b40b612438d","amp;dn":"Ivy+Manor+3+-+Tropical+Submission+%28BDSM+Latex+%26+Bondage%29+mpg","amp;tr":["udp%3A%2F%2Ftracker.openbittorrent.com%3A80","udp%3A%2F%2Fopen.demonii.com%3A1337","udp%3A%2F%2Ftracker.coppersurfer.tk%3A6969","udp%3A%2F%2Fexodus.desync.com%3A6969"],"infoHash":"0d2fee67d5908d71f1c9276a2f108b40b612438d","infoHashBuffer":{"type":"Buffer","data":[13,47,238,103,213,144,141,113,241,201,39,106,47,16,139,64,182,18,67,141]},"announce":[],"urlList":[]}}