{"title":"[NubileFilms] Dido Angel, Claire Dain (She Started This / 10.07.","uid":9016749,"size":181260625,"categoryP":"porn","categoryS":"movie_clips","magnet":"?xt=urn:btih:0f65ae9a151b64e5d5ffabec416c15a4977d6963&amp;dn=%5BNubileFilms%5D+Dido+Angel%2C+Claire+Dain+%28She+Started+This+%2F+10.07.&amp;tr=udp%3A%2F%2Ftracker.openbittorrent.com%3A80&amp;tr=udp%3A%2F%2Fopen.demonii.com%3A1337&amp;tr=udp%3A%2F%2Ftracker.coppersurfer.tk%3A6969&amp;tr=udp%3A%2F%2Fexodus.desync.com%3A6969","seeders":1,"leechers":0,"uploader":"chkm8te","files":1,"time":1381204428,"description":"[NubileFilms] Dido Angel, Claire Dain (She Started This / 10.07.2013)\n\nScreens: &lt;a href=&quot;\nhttp://xxxhost.me/viewer.php?file=r7anpnjc9wlv0j7zfe5g.jpg&quot; rel=&quot;nofollow&quot; target=&quot;_NEW&quot;&gt;\nhttp://xxxhost.me/viewer.php?file=r7anpnjc9wlv0j7zfe5g.jpg&lt;/a&gt;\n &lt;a href=&quot;\nhttp://xxxhost.me/viewer.php?file=vwzvvtyu3maggcpaibi5.jpg&quot; rel=&quot;nofollow&quot; target=&quot;_NEW&quot;&gt;\nhttp://xxxhost.me/viewer.php?file=vwzvvtyu3maggcpaibi5.jpg&lt;/a&gt;","torrent":{"xt":"urn:btih:0f65ae9a151b64e5d5ffabec416c15a4977d6963","amp;dn":"%5BNubileFilms%5D+Dido+Angel%2C+Claire+Dain+%28She+Started+This+%2F+10.07.","amp;tr":["udp%3A%2F%2Ftracker.openbittorrent.com%3A80","udp%3A%2F%2Fopen.demonii.com%3A1337","udp%3A%2F%2Ftracker.coppersurfer.tk%3A6969","udp%3A%2F%2Fexodus.desync.com%3A6969"],"infoHash":"0f65ae9a151b64e5d5ffabec416c15a4977d6963","infoHashBuffer":{"type":"Buffer","data":[15,101,174,154,21,27,100,229,213,255,171,236,65,108,21,164,151,125,105,99]},"announce":[],"urlList":[]}}