{"title":"Santa Claus Girl","uid":9832366,"size":158385645,"categoryP":"porn","categoryS":"pictures","magnet":"?xt=urn:btih:0fef61bc4a2388f12f6344406c12038152af06cb&amp;dn=Santa+Claus+Girl&amp;tr=udp%3A%2F%2Ftracker.openbittorrent.com%3A80&amp;tr=udp%3A%2F%2Fopen.demonii.com%3A1337&amp;tr=udp%3A%2F%2Ftracker.coppersurfer.tk%3A6969&amp;tr=udp%3A%2F%2Fexodus.desync.com%3A6969","seeders":1,"leechers":0,"uploader":"expressfile","files":128,"time":1395861954,"description":"Santa Claus Girl\n\nInfo:\n &lt;a href=&quot;\nhttp://fbdm.info/?p=2143&quot; rel=&quot;nofollow&quot; target=&quot;_NEW&quot;&gt;\nhttp://fbdm.info/?p=2143&lt;/a&gt;\n\nPlease seed and enjoy\n\nCheck all my torrents\n &lt;a href=&quot;\nhttp://thepiratebay.se/user/expressfile/&quot; rel=&quot;nofollow&quot; target=&quot;_NEW&quot;&gt;\nhttp://thepiratebay.se/user/expressfile/&lt;/a&gt;\n\n\n\n","torrent":{"xt":"urn:btih:0fef61bc4a2388f12f6344406c12038152af06cb","amp;dn":"Santa+Claus+Girl","amp;tr":["udp%3A%2F%2Ftracker.openbittorrent.com%3A80","udp%3A%2F%2Fopen.demonii.com%3A1337","udp%3A%2F%2Ftracker.coppersurfer.tk%3A6969","udp%3A%2F%2Fexodus.desync.com%3A6969"],"infoHash":"0fef61bc4a2388f12f6344406c12038152af06cb","infoHashBuffer":{"type":"Buffer","data":[15,239,97,188,74,35,136,241,47,99,68,64,108,18,3,129,82,175,6,203]},"announce":[],"urlList":[]}}