{"title":"AmateurLapdancer.Exotic.Teen.With.Perfect.Body.DVDRip.XxX.mp4","uid":9032620,"size":257182958,"categoryP":"porn","categoryS":"movie_clips","magnet":"?xt=urn:btih:2523fb3a511382ea7dd38043db7c4c077c832a9e&amp;dn=AmateurLapdancer.Exotic.Teen.With.Perfect.Body.DVDRip.XxX.mp4&amp;tr=udp%3A%2F%2Ftracker.openbittorrent.com%3A80&amp;tr=udp%3A%2F%2Fopen.demonii.com%3A1337&amp;tr=udp%3A%2F%2Ftracker.coppersurfer.tk%3A6969&amp;tr=udp%3A%2F%2Fexodus.desync.com%3A6969","seeders":1,"leechers":0,"uploader":"handsome_hulk1253","files":1,"time":1381454957,"description":"Screenshots\n &lt;a href=&quot;\nhttp://adultxpictures.com/xxx/4ES&quot; rel=&quot;nofollow&quot; target=&quot;_NEW&quot;&gt;\nhttp://adultxpictures.com/xxx/4ES&lt;/a&gt; &lt;a href=&quot;\nhttp://adultxpictures.com/xxx/4Et&quot; rel=&quot;nofollow&quot; target=&quot;_NEW&quot;&gt;\nhttp://adultxpictures.com/xxx/4Et&lt;/a&gt;\n","torrent":{"xt":"urn:btih:2523fb3a511382ea7dd38043db7c4c077c832a9e","amp;dn":"AmateurLapdancer.Exotic.Teen.With.Perfect.Body.DVDRip.XxX.mp4","amp;tr":["udp%3A%2F%2Ftracker.openbittorrent.com%3A80","udp%3A%2F%2Fopen.demonii.com%3A1337","udp%3A%2F%2Ftracker.coppersurfer.tk%3A6969","udp%3A%2F%2Fexodus.desync.com%3A6969"],"infoHash":"2523fb3a511382ea7dd38043db7c4c077c832a9e","infoHashBuffer":{"type":"Buffer","data":[37,35,251,58,81,19,130,234,125,211,128,67,219,124,76,7,124,131,42,158]},"announce":[],"urlList":[]}}