{"title":"Ted (HD 720p).m4v","uid":8111274,"size":3632155191,"categoryP":"video","categoryS":"hd___movies","magnet":"?xt=urn:btih:2e54599661af20a506c99007757720c614914e63&amp;dn=Ted+%28HD+720p%29.m4v&amp;tr=udp%3A%2F%2Ftracker.openbittorrent.com%3A80&amp;tr=udp%3A%2F%2Fopen.demonii.com%3A1337&amp;tr=udp%3A%2F%2Ftracker.coppersurfer.tk%3A6969&amp;tr=udp%3A%2F%2Fexodus.desync.com%3A6969","seeders":1,"leechers":0,"uploader":"arctictpb","files":1,"time":1360189848,"description":"Complete name                            : Ted (HD 720p).m4v\nFormat                                   : MPEG-4\nFormat profile                           : Base Media / Version 2\nCodec ID                                 : mp42\nFile size                                : 3.38 GiB\nDuration                                 : 1h 46mn\nOverall bit rate mode                    : Variable\nOverall bit rate                         : 4 566 Kbps\nMovie name                               : Ted\nPerformer                                : Seth MacFarlane, Mark Wahlberg, Mila Kunis, Giovanni Ribisi, Laura Vandervoort, Joel McHale, Bill Smitrovich, Matt Walsh, Bretton Manley, Alex Borstein, Patrick Warburton, Jessica Barth, Patrick Stewart, Jessica Stroup, Tara Strong\nGenre                                    : Comedy, Fantasy\nRecorded date                            : 2012-06-29\nEncoded date                             : UTC 2012-12-27 03:34:00\nTagged date                              : UTC 2012-12-29 21:42:15\nWriting application                      : HandBrake 5106svn 2012122501\nCover                                    : Yes\ndesc                                     : Family Guy creator Seth MacFarlane brings his boundary-pushing brand of humor to the big screen for the first time as writer, director and voice star of Ted. In the live action/CG-animated comedy, he tells the story of John Bennett, a grown man who must deal with the cherished teddy bear who came to life as the result of a childhood wish, and has refused to leave his side ever since.\n\nVideo #1\nID                                       : 1\nFormat                                   : AVC\nFormat/Info                              : Advanced Video Codec\nFormat profile                           : &lt;a class=&quot;__cf_email__&quot; href=&quot;/cdn-cgi/l/email-protection&quot; data-cfemail=&quot;da92b3bdb29a96e9f4eb&quot;&gt;[email&amp;#160;protected]&lt;/a&gt;&lt;script cf-hash='f9e31' type=&quot;text/javascript&quot;&gt;\n/* &lt;![CDATA[ */!function(){try{var t=&quot;currentScript&quot;in document?document.currentScript:function(){for(var t=document.getElementsByTagName(&quot;script&quot;),e=t.length;e--;)if(t[e].getAttribute(&quot;cf-hash&quot;))return t[e]}();if(t&amp;&amp;t.previousSibling){var e,r,n,i,c=t.previousSibling,a=c.getAttribute(&quot;data-cfemail&quot;);if(a){for(e=&quot;&quot;,r=parseInt(a.substr(0,2),16),n=2;a.length-n;n+=2)i=parseInt(a.substr(n,2),16)^r,e+=String.fromCharCode(i);e=document.createTextNode(e),c.parentNode.replaceChild(e,c)}}}catch(u){}}();/* ]]&gt; */&lt;/script&gt;\nFormat settings, CABAC                   : Yes\nFormat settings, ReFrames                : 4 frames\nCodec ID                                 : avc1\nCodec ID/Info                            : Advanced Video Coding\nDuration                                 : 1h 46mn\nBit rate mode                            : Variable\nBit rate                                 : 3 721 Kbps\nWidth                                    : 1 280 pixels\nHeight                                   : 688 pixels\nDisplay aspect ratio                     : 1.85:1\nFrame rate mode                          : Variable\nFrame rate                               : 23.976 fps\nMinimum frame rate                       : 18.431 fps\nMaximum frame rate                       : 23.981 fps\nColor space                              : YUV\nChroma subsampling                       : 4:2:0\nBit depth                                : 8 bits\nScan type                                : Progressive\nBits/(Pixel*Frame)                       : 0.176\nStream size                              : 2.76 GiB (81%)\nWriting library                          : x264 core 128\nEncoding settings                        : cabac=1 / ref=4 / deblock=1:0:0 / analyse=0x3:0x133 / me=umh / subme=10 / psy=1 / psy_rd=1.00:0.15 / mixed_ref=1 / me_range=32 / chroma_me=1 / trellis=2 / 8x8dct=1 / cqm=0 / deadzone=21,11 / fast_pskip=1 / chroma_qp_offset=-3 / threads=12 / lookahead_threads=2 / sliced_threads=0 / nr=0 / decimate=1 / interlaced=0 / bluray_compat=0 / constrained_intra=0 / bframes=4 / b_pyramid=2 / b_adapt=2 / b_bias=0 / direct=3 / weightb=1 / open_gop=0 / weightp=2 / keyint=300 / keyint_min=30 / scenecut=40 / intra_refresh=0 / rc_lookahead=60 / rc=crf / mbtree=1 / crf=18.0 / qcomp=0.60 / qpmin=4 / qpmax=69 / qpstep=4 / ip_ratio=1.40 / aq=1:1.00\nLanguage                                 : English\nEncoded date                             : UTC 2012-12-27 03:34:00\nTagged date                              : UTC 2012-12-27 06:33:11\nColor primaries                          : BT.709\nTransfer characteristics                 : BT.709\nMatrix coefficients                      : BT.709\n\nAudio #1\nID                                       : 2\nFormat                                   : AAC\nFormat/Info                              : Advanced Audio Codec\nFormat profile                           : LC\nCodec ID                                 : 40\nDuration                                 : 1h 46mn\nBit rate mode                            : Variable\nBit rate                                 : 196 Kbps\nMaximum bit rate                         : 324 Kbps\nChannel(s)                               : 2 channels\nChannel positions                        : Front: L R\nSampling rate                            : 48.0 KHz\nCompression mode                         : Lossy\nDelay relative to video                  : 83ms\nStream size                              : 149 MiB (4%)\nLanguage                                 : English\nEncoded date                             : UTC 2012-12-27 03:34:00\nTagged date                              : UTC 2012-12-27 06:33:11\n\nAudio #2\nID                                       : 3\nFormat                                   : AC-3\nFormat/Info                              : Audio Coding 3\nMode extension                           : CM (complete main)\nFormat settings, Endianness              : Big\nCodec ID                                 : ac-3\nDuration                                 : 1h 46mn\nBit rate mode                            : Constant\nBit rate                                 : 640 Kbps\nChannel(s)                               : 6 channels\nChannel positions                        : Front: L C R, Side: L R, LFE\nSampling rate                            : 48.0 KHz\nBit depth                                : 16 bits\nCompression mode                         : Lossy\nDelay relative to video                  : 83ms\nStream size                              : 485 MiB (14%)\nLanguage                                 : English\nEncoded date                             : UTC 2012-12-27 03:34:00\nTagged date                              : UTC 2012-12-27 06:33:11","torrent":{"xt":"urn:btih:2e54599661af20a506c99007757720c614914e63","amp;dn":"Ted+%28HD+720p%29.m4v","amp;tr":["udp%3A%2F%2Ftracker.openbittorrent.com%3A80","udp%3A%2F%2Fopen.demonii.com%3A1337","udp%3A%2F%2Ftracker.coppersurfer.tk%3A6969","udp%3A%2F%2Fexodus.desync.com%3A6969"],"infoHash":"2e54599661af20a506c99007757720c614914e63","infoHashBuffer":{"type":"Buffer","data":[46,84,89,150,97,175,32,165,6,201,144,7,117,119,32,198,20,145,78,99]},"announce":[],"urlList":[]}}