{"title":"[FFF] Chuunibyou demo Koi ga Shitai! - Vol.06 [BD][720p-AAC]","uid":9495728,"size":841735758,"categoryP":"video","categoryS":"hd___tv_shows","magnet":"?xt=urn:btih:32c1037998ea57a4710fe8d9f11cd922f330c024&amp;dn=%5BFFF%5D+Chuunibyou+demo+Koi+ga+Shitai%21+-+Vol.06+%5BBD%5D%5B720p-AAC%5D&amp;tr=udp%3A%2F%2Ftracker.openbittorrent.com%3A80&amp;tr=udp%3A%2F%2Fopen.demonii.com%3A1337&amp;tr=udp%3A%2F%2Ftracker.coppersurfer.tk%3A6969&amp;tr=udp%3A%2F%2Fexodus.desync.com%3A6969","seeders":1,"leechers":2,"uploader":"darkj6","files":2,"time":1390101125,"description":" ______   _______  ______    ___   _      ___  --------|\n|      | |   _   ||    _ |  |   | | |    |   ||   |----|    \n|  _    ||  |_|  ||   | ||  |   |_| |    |   ||   |___ \n| | |   ||       ||   |_||_ |      _|    |   ||    _  |\n| |_|   ||       ||    __  ||     |_  ___|   ||   | | |\n|       ||   _   ||   |  | ||    _  ||       ||   |_| |\n|______| |__| |__||___|  |_||___| |_||_______||_______|","torrent":{"xt":"urn:btih:32c1037998ea57a4710fe8d9f11cd922f330c024","amp;dn":"%5BFFF%5D+Chuunibyou+demo+Koi+ga+Shitai%21+-+Vol.06+%5BBD%5D%5B720p-AAC%5D","amp;tr":["udp%3A%2F%2Ftracker.openbittorrent.com%3A80","udp%3A%2F%2Fopen.demonii.com%3A1337","udp%3A%2F%2Ftracker.coppersurfer.tk%3A6969","udp%3A%2F%2Fexodus.desync.com%3A6969"],"infoHash":"32c1037998ea57a4710fe8d9f11cd922f330c024","infoHashBuffer":{"type":"Buffer","data":[50,193,3,121,152,234,87,164,113,15,232,217,241,28,217,34,243,48,192,36]},"announce":[],"urlList":[]}}