{"title":"[720p].GloryHole - Beverly Paige","uid":7508912,"size":716126617,"categoryP":"porn","categoryS":"hd___movies","magnet":"?xt=urn:btih:38d45cc3e6561af025b4903d4e16354000ec0283&amp;dn=%5B720p%5D.GloryHole+-+Beverly+Paige&amp;tr=udp%3A%2F%2Ftracker.openbittorrent.com%3A80&amp;tr=udp%3A%2F%2Fopen.demonii.com%3A1337&amp;tr=udp%3A%2F%2Ftracker.coppersurfer.tk%3A6969&amp;tr=udp%3A%2F%2Fexodus.desync.com%3A6969","seeders":1,"leechers":0,"uploader":"kelvin09","files":1,"time":1344258294,"description":"GloryHole - Beverly Paige\n\n  &lt;a href=&quot;\nhttp://www.picrak.com/viewer.php?file=89668875175107239771.jpg&quot; rel=&quot;nofollow&quot; target=&quot;_NEW&quot;&gt;\nhttp://www.picrak.com/viewer.php?file=89668875175107239771.jpg&lt;/a&gt;\n\n  &lt;a href=&quot;\nhttp://www.picrak.com/viewer.php?file=87750912450549978606.jpg&quot; rel=&quot;nofollow&quot; target=&quot;_NEW&quot;&gt;\nhttp://www.picrak.com/viewer.php?file=87750912450549978606.jpg&lt;/a&gt;\n\n\nBeverly Paige has always flirted with the black customers while shaking her fat tits at the strip club. The flirting has always been just that-flirting and no more. You can only tease a hungry lion so may times before it attacks....and today it happens. Beverly is jiggling those massive mams for massive money when a couple of ballsy black patrons decide to ty their luck. Beverly has never, ever had black cock introduced to her pink taco, or mouth, and today's as good as any day to break that sin. Beverly sucks on each black cock, while , mind you, she ignores the fact that she's on the clock and the club's management might not look kindly on all this. Beverly doesn't give a fuck and she continues to slobber each black know via the glory hole. The hole gets the ride of its like when Beverly backs that plump ass up, and gets her pussy filled with every inch of those anonymous black cocks. Beverly Paige is no longer a stranger to black cock and she's just put in for a transfer to the strip club in Compton.\t","torrent":{"xt":"urn:btih:38d45cc3e6561af025b4903d4e16354000ec0283","amp;dn":"%5B720p%5D.GloryHole+-+Beverly+Paige","amp;tr":["udp%3A%2F%2Ftracker.openbittorrent.com%3A80","udp%3A%2F%2Fopen.demonii.com%3A1337","udp%3A%2F%2Ftracker.coppersurfer.tk%3A6969","udp%3A%2F%2Fexodus.desync.com%3A6969"],"infoHash":"38d45cc3e6561af025b4903d4e16354000ec0283","infoHashBuffer":{"type":"Buffer","data":[56,212,92,195,230,86,26,240,37,180,144,61,78,22,53,64,0,236,2,131]},"announce":[],"urlList":[]}}