{"title":"Wendy Fiore - White Leather Couch2","uid":7480240,"size":12161812,"categoryP":"porn","categoryS":"pictures","magnet":"?xt=urn:btih:49ca6250f41d2f5cf944e07309d1321723b02974&amp;dn=Wendy+Fiore+-+White+Leather+Couch2&amp;tr=udp%3A%2F%2Ftracker.openbittorrent.com%3A80&amp;tr=udp%3A%2F%2Fopen.demonii.com%3A1337&amp;tr=udp%3A%2F%2Ftracker.coppersurfer.tk%3A6969&amp;tr=udp%3A%2F%2Fexodus.desync.com%3A6969","seeders":1,"leechers":0,"uploader":"hancelove","files":-1,"time":1343412358,"description":"Wendy Fiore - White Leather Couch2\n\n24 pics - File size: 11.6 Mb\n &lt;a href=&quot;\nhttp://x-busty.ru/wendy_fiore/171-white-leather-couch2.html&quot; rel=&quot;nofollow&quot; target=&quot;_NEW&quot;&gt;\nhttp://x-busty.ru/wendy_fiore/171-white-leather-couch2.html&lt;/a&gt;","torrent":{"xt":"urn:btih:49ca6250f41d2f5cf944e07309d1321723b02974","amp;dn":"Wendy+Fiore+-+White+Leather+Couch2","amp;tr":["udp%3A%2F%2Ftracker.openbittorrent.com%3A80","udp%3A%2F%2Fopen.demonii.com%3A1337","udp%3A%2F%2Ftracker.coppersurfer.tk%3A6969","udp%3A%2F%2Fexodus.desync.com%3A6969"],"infoHash":"49ca6250f41d2f5cf944e07309d1321723b02974","infoHashBuffer":{"type":"Buffer","data":[73,202,98,80,244,29,47,92,249,68,224,115,9,209,50,23,35,176,41,116]},"announce":[],"urlList":[]}}