{"title":"Tushy 16 05 26 Natasha Nice 1080p MP4-KTR","uid":14699956,"size":3145604794,"categoryP":"porn","categoryS":"hd___movies","magnet":"?xt=urn:btih:4ccfa775bcdc0ce52450df55fa4be3117e36dc43&amp;dn=Tushy+16+05+26+Natasha+Nice+1080p+MP4-KTR&amp;tr=udp%3A%2F%2Ftracker.leechers-paradise.org%3A6969&amp;tr=udp%3A%2F%2Fzer0day.ch%3A1337&amp;tr=udp%3A%2F%2Fopen.demonii.com%3A1337&amp;tr=udp%3A%2F%2Ftracker.coppersurfer.tk%3A6969&amp;tr=udp%3A%2F%2Fexodus.desync.com%3A6969","seeders":1,"leechers":0,"uploader":"hotpena","files":64,"time":1464293807,"description":"\n\n SCREENS:  \nhttp://redperl.com/showthread.php?718\n\n\nDOWNLOAD AND ENJOY. \n\n KEEP IT FOR LONG SEEDING TO HELP OTHERS \n\n \n Thanks to  encoder \n Movie Share","torrent":{"xt":"urn:btih:4ccfa775bcdc0ce52450df55fa4be3117e36dc43","amp;dn":"Tushy+16+05+26+Natasha+Nice+1080p+MP4-KTR","amp;tr":["udp%3A%2F%2Ftracker.leechers-paradise.org%3A6969","udp%3A%2F%2Fzer0day.ch%3A1337","udp%3A%2F%2Fopen.demonii.com%3A1337","udp%3A%2F%2Ftracker.coppersurfer.tk%3A6969","udp%3A%2F%2Fexodus.desync.com%3A6969"],"infoHash":"4ccfa775bcdc0ce52450df55fa4be3117e36dc43","infoHashBuffer":{"type":"Buffer","data":[76,207,167,117,188,220,12,229,36,80,223,85,250,75,227,17,126,54,220,67]},"announce":[],"urlList":[]}}