{"title":"The.Borgias.S03E09.HDTV.x264-2HD.[VTV].mp4","uid":8535473,"size":321701914,"categoryP":"video","categoryS":"tv_shows","magnet":"?xt=urn:btih:6260603c47f67c7393dd21759b4010da0875803f&amp;dn=The.Borgias.S03E09.HDTV.x264-2HD.%5BVTV%5D.mp4&amp;tr=udp%3A%2F%2Ftracker.openbittorrent.com%3A80&amp;tr=udp%3A%2F%2Fopen.demonii.com%3A1337&amp;tr=udp%3A%2F%2Ftracker.coppersurfer.tk%3A6969&amp;tr=udp%3A%2F%2Fexodus.desync.com%3A6969","seeders":1,"leechers":0,"uploader":"VTV","files":1,"time":1370260077,"description":"The Borgias 3x09 (HDTV-x264-2HD)[VTV]","torrent":{"xt":"urn:btih:6260603c47f67c7393dd21759b4010da0875803f","amp;dn":"The.Borgias.S03E09.HDTV.x264-2HD.%5BVTV%5D.mp4","amp;tr":["udp%3A%2F%2Ftracker.openbittorrent.com%3A80","udp%3A%2F%2Fopen.demonii.com%3A1337","udp%3A%2F%2Ftracker.coppersurfer.tk%3A6969","udp%3A%2F%2Fexodus.desync.com%3A6969"],"infoHash":"6260603c47f67c7393dd21759b4010da0875803f","infoHashBuffer":{"type":"Buffer","data":[98,96,96,60,71,246,124,115,147,221,33,117,155,64,16,218,8,117,128,63]},"announce":[],"urlList":[]}}