{"title":"Liquid Metal 2 - Morgan Strebler","uid":8155571,"size":186802939,"categoryP":"video","categoryS":"other","magnet":"?xt=urn:btih:66f935cbb5fb77688cf88837ea6df7d3a1f826cb&amp;dn=Liquid+Metal+2+-+Morgan+Strebler&amp;tr=udp%3A%2F%2Ftracker.openbittorrent.com%3A80&amp;tr=udp%3A%2F%2Fopen.demonii.com%3A1337&amp;tr=udp%3A%2F%2Ftracker.coppersurfer.tk%3A6969&amp;tr=udp%3A%2F%2Fexodus.desync.com%3A6969","seeders":1,"leechers":0,"uploader":"ThalesMan","files":1,"time":1361155797,"description":"Liquid Metal 2 by Morgan Strebler\n\n\nI just want to ask to anyone that sees this page, if you have Wayne Houchin's Control 2.0 and/or Thread, please upload and comment the link on this page. I found a couple of torrents uploaded by a user named bernar_bus, but they're out of seeds. Any other magic tutorial is welcomed too.\n\nThanks ;D","torrent":{"xt":"urn:btih:66f935cbb5fb77688cf88837ea6df7d3a1f826cb","amp;dn":"Liquid+Metal+2+-+Morgan+Strebler","amp;tr":["udp%3A%2F%2Ftracker.openbittorrent.com%3A80","udp%3A%2F%2Fopen.demonii.com%3A1337","udp%3A%2F%2Ftracker.coppersurfer.tk%3A6969","udp%3A%2F%2Fexodus.desync.com%3A6969"],"infoHash":"66f935cbb5fb77688cf88837ea6df7d3a1f826cb","infoHashBuffer":{"type":"Buffer","data":[102,249,53,203,181,251,119,104,140,248,136,55,234,109,247,211,161,248,38,203]},"announce":[],"urlList":[]}}