{"title":"Electrosluts--ES-34898 Aiden Starr and Mona Wales","uid":9798575,"size":4065467926,"categoryP":"porn","categoryS":"hd___movies","magnet":"?xt=urn:btih:7c44f78bf01a190322fd53708f0938c756ffc8a0&amp;dn=Electrosluts--ES-34898+Aiden+Starr+and+Mona+Wales&amp;tr=udp%3A%2F%2Ftracker.openbittorrent.com%3A80&amp;tr=udp%3A%2F%2Fopen.demonii.com%3A1337&amp;tr=udp%3A%2F%2Ftracker.coppersurfer.tk%3A6969&amp;tr=udp%3A%2F%2Fexodus.desync.com%3A6969","seeders":1,"leechers":0,"uploader":"merzedes","files":-1,"time":1395351207,"description":"Slim Blonde Amateur Covered in Electricity and Ass Fucked Live!!\n\nMar 20, 2014 - Performers: Aiden Starr  and  Mona Wales \n\n\nMed, Hi and HD MP4 + Pics.\n\n\nMona Wales is a porn amateur and a genuine pervert. At the hands of Aiden Starr she gets covered in EMS pads and pussy filled with an electro plug, then made to cum hard! She takes the zappers and is made to zap herself. Aiden tickles her and turns her into a pony, shocking Mona's firm ass as she rides around the room. Mona takes the samurai deep in her ass for a hard anal electro fuck, and is rewarded with Aiden's perfect cunt in her face - zapping her cute tongue with conductivity from the body plate of course! This slut takes Aiden's cum all over her face and then gets zapped some more!\n\nScreens &lt;a href=&quot;\nhttp://www.electrosluts.com/site/shoot.jsp?shootId=34898&quot; rel=&quot;nofollow&quot; target=&quot;_NEW&quot;&gt;\nhttp://www.electrosluts.com/site/shoot.jsp?shootId=34898&lt;/a&gt;\n\n13 000 uploads and counting, 14k here we come :) And as usual, if you still like what Shallow2 and I upload, how about leaving us a nice comment below ? :)\n\n\nAny Questions ?? Read our FAQ!!\n &lt;a href=&quot;\nhttp://image.bayimg.com/eaea7e9e982a9a677d61e4f5aaf93b7643bd6eeb.jpg&quot; rel=&quot;nofollow&quot; target=&quot;_NEW&quot;&gt;\nhttp://image.bayimg.com/eaea7e9e982a9a677d61e4f5aaf93b7643bd6eeb.jpg&lt;/a&gt;\n\n\nCheers  :-)  \n\n\n","torrent":{"xt":"urn:btih:7c44f78bf01a190322fd53708f0938c756ffc8a0","amp;dn":"Electrosluts--ES-34898+Aiden+Starr+and+Mona+Wales","amp;tr":["udp%3A%2F%2Ftracker.openbittorrent.com%3A80","udp%3A%2F%2Fopen.demonii.com%3A1337","udp%3A%2F%2Ftracker.coppersurfer.tk%3A6969","udp%3A%2F%2Fexodus.desync.com%3A6969"],"infoHash":"7c44f78bf01a190322fd53708f0938c756ffc8a0","infoHashBuffer":{"type":"Buffer","data":[124,68,247,139,240,26,25,3,34,253,83,112,143,9,56,199,86,255,200,160]},"announce":[],"urlList":[]}}