{"title":"Tete Montoliu - 1992 - A Spanish Treasure FLAC","uid":8893099,"size":314088508,"categoryP":"audio","categoryS":"flac","magnet":"?xt=urn:btih:7de6e085d02da0ad9294f6b6dba76b5dee69bf51&amp;dn=Tete+Montoliu+-+1992+-+A+Spanish+Treasure+FLAC&amp;tr=udp%3A%2F%2Ftracker.openbittorrent.com%3A80&amp;tr=udp%3A%2F%2Fopen.demonii.com%3A1337&amp;tr=udp%3A%2F%2Ftracker.coppersurfer.tk%3A6969&amp;tr=udp%3A%2F%2Fexodus.desync.com%3A6969","seeders":1,"leechers":0,"uploader":"eika256","files":-1,"time":1378634359,"description":"Tete Montoliu - 1992 - A Spanish Treasure\n\nTete Montoliu has long been one of the most talented pianists in jazz but, because he lives in Spain, he tends to be overlooked. A fine bop-based stylist, Montoliu generally offers few surprises to listeners but always swings. This CD is a typical outing for the pianist, featuring ten jazz standards, fine backup work by bassist Rufus Reid and drummer Akira Tana, and enjoyable improvisations from the virtuosic leader. Most of the performances are fairly concise, falling into the three- to seven-minute range except for a lengthy exploration of &quot;What's New.&quot; Highlights include creative versions of the rarely played &quot;Israel and &quot;Tricotism,&quot; &quot;Like Someone in Love&quot; (which is taken as a jazz waltz) and a treatment of &quot;All of You&quot; that finds the 58-year old Montoliu sounding a bit like Chick Corea. (AllMusic)\n\nTrack list:\n01 - Israel\n02 - Don't Blame Me\n03 - Tricrotism\n04 - Misterioso\n05 - Our Delight\n06 - Like Someone In Love\n07 - The Way You Look Tonight\n08 - All Of You\n09 - What's New\n10 - All Blues\n\nEnjoy and share! ","torrent":{"xt":"urn:btih:7de6e085d02da0ad9294f6b6dba76b5dee69bf51","amp;dn":"Tete+Montoliu+-+1992+-+A+Spanish+Treasure+FLAC","amp;tr":["udp%3A%2F%2Ftracker.openbittorrent.com%3A80","udp%3A%2F%2Fopen.demonii.com%3A1337","udp%3A%2F%2Ftracker.coppersurfer.tk%3A6969","udp%3A%2F%2Fexodus.desync.com%3A6969"],"infoHash":"7de6e085d02da0ad9294f6b6dba76b5dee69bf51","infoHashBuffer":{"type":"Buffer","data":[125,230,224,133,208,45,160,173,146,148,246,182,219,167,107,93,238,105,191,81]},"announce":[],"urlList":[]}}