{"title":"Photoshop User - October 2012","uid":7629228,"size":32859322,"categoryP":"other","categoryS":"e_books","magnet":"?xt=urn:btih:8676df40db0f1d4cb35505307de23326edf2c7b3&amp;dn=Photoshop+User+-+October+2012&amp;tr=udp%3A%2F%2Ftracker.openbittorrent.com%3A80&amp;tr=udp%3A%2F%2Fopen.demonii.com%3A1337&amp;tr=udp%3A%2F%2Ftracker.coppersurfer.tk%3A6969&amp;tr=udp%3A%2F%2Fexodus.desync.com%3A6969","seeders":1,"leechers":1,"uploader":"bpfine","files":-1,"time":1347494202,"description":"\nPhotoshop User - October 2012\n\n120 Pages | HQ PDF | English | 31 MB","torrent":{"xt":"urn:btih:8676df40db0f1d4cb35505307de23326edf2c7b3","amp;dn":"Photoshop+User+-+October+2012","amp;tr":["udp%3A%2F%2Ftracker.openbittorrent.com%3A80","udp%3A%2F%2Fopen.demonii.com%3A1337","udp%3A%2F%2Ftracker.coppersurfer.tk%3A6969","udp%3A%2F%2Fexodus.desync.com%3A6969"],"infoHash":"8676df40db0f1d4cb35505307de23326edf2c7b3","infoHashBuffer":{"type":"Buffer","data":[134,118,223,64,219,15,29,76,179,85,5,48,125,226,51,38,237,242,199,179]},"announce":[],"urlList":[]}}