{"title":"2.Broke.Girls.S03E13.HDTV.x264-LOL","uid":9474989,"size":211383137,"categoryP":"video","categoryS":"tv_shows","magnet":"?xt=urn:btih:8e957e492446dcce99073422d4ab81252520292f&amp;dn=2.Broke.Girls.S03E13.HDTV.x264-LOL&amp;tr=udp%3A%2F%2Ftracker.openbittorrent.com%3A80&amp;tr=udp%3A%2F%2Fopen.demonii.com%3A1337&amp;tr=udp%3A%2F%2Ftracker.coppersurfer.tk%3A6969&amp;tr=udp%3A%2F%2Fexodus.desync.com%3A6969","seeders":1,"leechers":0,"uploader":".SceNe.","files":2,"time":1389670754,"description":"2.Broke.Girls.S03E13.HDTV.x264-LOL","torrent":{"xt":"urn:btih:8e957e492446dcce99073422d4ab81252520292f","amp;dn":"2.Broke.Girls.S03E13.HDTV.x264-LOL","amp;tr":["udp%3A%2F%2Ftracker.openbittorrent.com%3A80","udp%3A%2F%2Fopen.demonii.com%3A1337","udp%3A%2F%2Ftracker.coppersurfer.tk%3A6969","udp%3A%2F%2Fexodus.desync.com%3A6969"],"infoHash":"8e957e492446dcce99073422d4ab81252520292f","infoHashBuffer":{"type":"Buffer","data":[142,149,126,73,36,70,220,206,153,7,52,34,212,171,129,37,37,32,41,47]},"announce":[],"urlList":[]}}