{"title":"Hustler xxx Magazine March_2011","uid":6079147,"size":60154574,"categoryP":"other","categoryS":"e_books","magnet":"?xt=urn:btih:90f9dbb8a54619c4dae46694f303fee26919151a&amp;dn=Hustler+xxx+Magazine+March_2011&amp;tr=udp%3A%2F%2Ftracker.openbittorrent.com%3A80&amp;tr=udp%3A%2F%2Fopen.demonii.com%3A1337&amp;tr=udp%3A%2F%2Ftracker.coppersurfer.tk%3A6969&amp;tr=udp%3A%2F%2Fexodus.desync.com%3A6969","seeders":1,"leechers":0,"uploader":"LoStXxTrAgIcXx","files":-1,"time":1294029317,"description":"Hustler xxx Magazine March_2011","torrent":{"xt":"urn:btih:90f9dbb8a54619c4dae46694f303fee26919151a","amp;dn":"Hustler+xxx+Magazine+March_2011","amp;tr":["udp%3A%2F%2Ftracker.openbittorrent.com%3A80","udp%3A%2F%2Fopen.demonii.com%3A1337","udp%3A%2F%2Ftracker.coppersurfer.tk%3A6969","udp%3A%2F%2Fexodus.desync.com%3A6969"],"infoHash":"90f9dbb8a54619c4dae46694f303fee26919151a","infoHashBuffer":{"type":"Buffer","data":[144,249,219,184,165,70,25,196,218,228,102,148,243,3,254,226,105,25,21,26]},"announce":[],"urlList":[]}}