{"title":"WoodmanCastingX - Natacha (Ukrainian Teacher)","uid":12597938,"size":158512873,"categoryP":"porn","categoryS":"movie_clips","magnet":"?xt=urn:btih:927212cbe9512aaa84d03beba43596c97c8cf625&amp;dn=WoodmanCastingX+-+Natacha+%28Ukrainian+Teacher%29&amp;tr=udp%3A%2F%2Ftracker.leechers-paradise.org%3A6969&amp;tr=udp%3A%2F%2Fzer0day.ch%3A1337&amp;tr=udp%3A%2F%2Fopen.demonii.com%3A1337&amp;tr=udp%3A%2F%2Ftracker.coppersurfer.tk%3A6969&amp;tr=udp%3A%2F%2Fexodus.desync.com%3A6969","seeders":1,"leechers":0,"uploader":"Ctrlme","files":2,"time":1445285082,"description":"------------------------------------------------------------\r\n            ....... : Screenshots : .......    \r\n------------------------------------------------------------ \nhttp://imgsay.com/?v=173626\r\n\r\n------------------------------------------------------------\r\n... : If you like this torrent, please post a comment!  :...\r\n... : Greets to our Friends at TPB, PL, ET, KAT &amp; 1337x :...\r\n... :            Don't forget to seed                   :...\r\n------------------------------------------------------------\r\n        ... : Stay connected with our uploads : ...        \r\n                  http://youpornshare.com\r\n------------------------------------------------------------\r\n                                             We ♥ Torrents!","torrent":{"xt":"urn:btih:927212cbe9512aaa84d03beba43596c97c8cf625","amp;dn":"WoodmanCastingX+-+Natacha+%28Ukrainian+Teacher%29","amp;tr":["udp%3A%2F%2Ftracker.leechers-paradise.org%3A6969","udp%3A%2F%2Fzer0day.ch%3A1337","udp%3A%2F%2Fopen.demonii.com%3A1337","udp%3A%2F%2Ftracker.coppersurfer.tk%3A6969","udp%3A%2F%2Fexodus.desync.com%3A6969"],"infoHash":"927212cbe9512aaa84d03beba43596c97c8cf625","infoHashBuffer":{"type":"Buffer","data":[146,114,18,203,233,81,42,170,132,208,59,235,164,53,150,201,124,140,246,37]},"announce":[],"urlList":[]}}