{"title":"[HomePornFrames]Latin - Latina American Teen Couple [.mp4]","uid":14802859,"size":474366945,"categoryP":"porn","categoryS":"movie_clips","magnet":"?xt=urn:btih:98413dacf540f23420936686b00a71e8f15d7e28&amp;dn=+%5BHomePornFrames%5DLatin+-+Latina+American+Teen+Couple+%5B.mp4%5D+&amp;tr=udp%3A%2F%2Ftracker.leechers-paradise.org%3A6969&amp;tr=udp%3A%2F%2Fzer0day.ch%3A1337&amp;tr=udp%3A%2F%2Fopen.demonii.com%3A1337&amp;tr=udp%3A%2F%2Ftracker.coppersurfer.tk%3A6969&amp;tr=udp%3A%2F%2Fexodus.desync.com%3A6969","seeders":1,"leechers":0,"uploader":"LucasCar","files":1,"time":1465142280,"description":"[HomePornFrames]Latin - Latina American Teen Couple [.mp4] \r\n \nhttp://voyeurimage.org/img-57542fddba2bf.html\r\n\r\n\r\n\r\n★ ★ ★  For more Exclusive Porn please visit ★ ★ ★\r\n     \nhttps://thepiratebay.org/user/LucasCar","torrent":{"xt":"urn:btih:98413dacf540f23420936686b00a71e8f15d7e28","amp;dn":"+%5BHomePornFrames%5DLatin+-+Latina+American+Teen+Couple+%5B.mp4%5D+","amp;tr":["udp%3A%2F%2Ftracker.leechers-paradise.org%3A6969","udp%3A%2F%2Fzer0day.ch%3A1337","udp%3A%2F%2Fopen.demonii.com%3A1337","udp%3A%2F%2Ftracker.coppersurfer.tk%3A6969","udp%3A%2F%2Fexodus.desync.com%3A6969"],"infoHash":"98413dacf540f23420936686b00a71e8f15d7e28","infoHashBuffer":{"type":"Buffer","data":[152,65,61,172,245,64,242,52,32,147,102,134,176,10,113,232,241,93,126,40]},"announce":[],"urlList":[]}}