{"title":"TeenBFF - Tantalizing Threesome Tasha Reign, Holly Michaels","uid":8139436,"size":476472361,"categoryP":"porn","categoryS":"movie_clips","magnet":"?xt=urn:btih:9c9b80bbea95773d3138ebcbb4972bc4c43bab53&amp;dn=TeenBFF+-+Tantalizing+Threesome+Tasha+Reign%2C+Holly+Michaels&amp;tr=udp%3A%2F%2Ftracker.openbittorrent.com%3A80&amp;tr=udp%3A%2F%2Fopen.demonii.com%3A1337&amp;tr=udp%3A%2F%2Ftracker.coppersurfer.tk%3A6969&amp;tr=udp%3A%2F%2Fexodus.desync.com%3A6969","seeders":1,"leechers":1,"uploader":"R0thschild","files":1,"time":1360778358,"description":"Gallery: \n &lt;a href=&quot;\nhttp://hqpdb.com/viewtopic.php?f=43&amp;t=21348&quot; rel=&quot;nofollow&quot; target=&quot;_NEW&quot;&gt;\nhttp://hqpdb.com/viewtopic.php?f=43&amp;t=21348&lt;/a&gt;\n\n------------------------------------------\n         My torrents at thePiratebay\n------------------------------------------\n   &lt;a href=&quot;\nhttp://thepiratebay.se/user/R0thschild/&quot; rel=&quot;nofollow&quot; target=&quot;_NEW&quot;&gt;\nhttp://thepiratebay.se/user/R0thschild/&lt;/a&gt;\t","torrent":{"xt":"urn:btih:9c9b80bbea95773d3138ebcbb4972bc4c43bab53","amp;dn":"TeenBFF+-+Tantalizing+Threesome+Tasha+Reign%2C+Holly+Michaels","amp;tr":["udp%3A%2F%2Ftracker.openbittorrent.com%3A80","udp%3A%2F%2Fopen.demonii.com%3A1337","udp%3A%2F%2Ftracker.coppersurfer.tk%3A6969","udp%3A%2F%2Fexodus.desync.com%3A6969"],"infoHash":"9c9b80bbea95773d3138ebcbb4972bc4c43bab53","infoHashBuffer":{"type":"Buffer","data":[156,155,128,187,234,149,119,61,49,56,235,203,180,151,43,196,196,59,171,83]},"announce":[],"urlList":[]}}