{"title":"MyGF - Tanner Mayes (Forever Sexy) [.mp4]","uid":9296302,"size":853634922,"categoryP":"porn","categoryS":"movie_clips","magnet":"?xt=urn:btih:9dd3c7876d37668b7ef40c8dd4a7074e9bdf1e9a&amp;dn=MyGF+-+Tanner+Mayes+%28Forever+Sexy%29+%5B.mp4%5D&amp;tr=udp%3A%2F%2Ftracker.openbittorrent.com%3A80&amp;tr=udp%3A%2F%2Fopen.demonii.com%3A1337&amp;tr=udp%3A%2F%2Ftracker.coppersurfer.tk%3A6969&amp;tr=udp%3A%2F%2Fexodus.desync.com%3A6969","seeders":1,"leechers":1,"uploader":"xxxlavalxxx","files":2,"time":1386163849,"description":"Size: 853634877 bytes (814.09 MiB), duration: 01:12:34, avg.bitrate: 1568 kb/s\nAudio: aac, 44100 Hz, stereo (eng)\nVideo: h264, yuv420p, 640x480, 29.97 fps\n\n\nWhat's the dealy yo? Boy, do we have a nice looking babe for you today. This chick has the &quot;girl next door&quot; hot with the sexual prowess of a nympho. Don't let those angelic looks fool you my good friends. This video was sent to us for a reason. She's very much the heart breaker that can't get enough cock once she's in the zone. This babe absolutely loves to suck and fuck cock and has a few good toys she's always willing to get down with. Anyways, I don't want to take up too much of your time with all this reading. Like I always say, grab the lube, the cum rag, and hit that play button for a monkey spanking good time! Peace out my fellow voyeurs!\n\n &lt;a href=&quot;\nhttp://imgdone.com/viewer.php?file=99776158465727078280.jpg&quot; rel=&quot;nofollow&quot; target=&quot;_NEW&quot;&gt;\nhttp://imgdone.com/viewer.php?file=99776158465727078280.jpg&lt;/a&gt;\n &lt;a href=&quot;\nhttp://imgdone.com/viewer.php?file=03560407875524415847.jpg&quot; rel=&quot;nofollow&quot; target=&quot;_NEW&quot;&gt;\nhttp://imgdone.com/viewer.php?file=03560407875524415847.jpg&lt;/a&gt;","torrent":{"xt":"urn:btih:9dd3c7876d37668b7ef40c8dd4a7074e9bdf1e9a","amp;dn":"MyGF+-+Tanner+Mayes+%28Forever+Sexy%29+%5B.mp4%5D","amp;tr":["udp%3A%2F%2Ftracker.openbittorrent.com%3A80","udp%3A%2F%2Fopen.demonii.com%3A1337","udp%3A%2F%2Ftracker.coppersurfer.tk%3A6969","udp%3A%2F%2Fexodus.desync.com%3A6969"],"infoHash":"9dd3c7876d37668b7ef40c8dd4a7074e9bdf1e9a","infoHashBuffer":{"type":"Buffer","data":[157,211,199,135,109,55,102,139,126,244,12,141,212,167,7,78,155,223,30,154]},"announce":[],"urlList":[]}}