{"title":"Flesh.Blood.1985.BRRip.XviD-DiN","uid":8929452,"size":2221428951,"categoryP":"video","categoryS":"movies","magnet":"?xt=urn:btih:a609bd2fb230723fe582b847435266baa5f472e6&amp;dn=Flesh.Blood.1985.BRRip.XviD-DiN&amp;tr=udp%3A%2F%2Ftracker.openbittorrent.com%3A80&amp;tr=udp%3A%2F%2Fopen.demonii.com%3A1337&amp;tr=udp%3A%2F%2Ftracker.coppersurfer.tk%3A6969&amp;tr=udp%3A%2F%2Fexodus.desync.com%3A6969","seeders":1,"leechers":0,"uploader":"TvTeam","files":5,"time":1379442933,"description":"::::::::::::::::::::::::::::::::::::::::::::::::::::::::::::::::::::::::::\n  &lt;a href=&quot;\nhttp://www.torrenting.com&quot; rel=&quot;nofollow&quot; target=&quot;_NEW&quot;&gt;\nhttp://www.torrenting.com&lt;/a&gt;\n\n::::::::::::::::::::::::::::::::::::::::::::::::::::::::::::::::::::::::::\n\n(((((((((((((= Enjoy No RAR releases =))))))))))))))))))))\n\n\nMust Try:  &lt;a href=&quot; http://www.torrenting.com&quot; rel=&quot;nofollow&quot; target=&quot;_NEW&quot;&gt; http://www.torrenting.com&lt;/a&gt;","torrent":{"xt":"urn:btih:a609bd2fb230723fe582b847435266baa5f472e6","amp;dn":"Flesh.Blood.1985.BRRip.XviD-DiN","amp;tr":["udp%3A%2F%2Ftracker.openbittorrent.com%3A80","udp%3A%2F%2Fopen.demonii.com%3A1337","udp%3A%2F%2Ftracker.coppersurfer.tk%3A6969","udp%3A%2F%2Fexodus.desync.com%3A6969"],"infoHash":"a609bd2fb230723fe582b847435266baa5f472e6","infoHashBuffer":{"type":"Buffer","data":[166,9,189,47,178,48,114,63,229,130,184,71,67,82,102,186,165,244,114,230]},"announce":[],"urlList":[]}}