{"title":"Bleachers - I Wanna Get Better (Mp4) (1080p) (Lil Jimmy)","uid":10749106,"size":73666358,"categoryP":"video","categoryS":"music_videos","magnet":"?xt=urn:btih:a6898307d2994eace9e1e2c41fff36b094ff168d&amp;dn=Bleachers+-+I+Wanna+Get+Better+%28Mp4%29+%281080p%29+%28Lil+Jimmy%29&amp;tr=udp%3A%2F%2Ftracker.openbittorrent.com%3A80&amp;tr=udp%3A%2F%2Fopen.demonii.com%3A1337&amp;tr=udp%3A%2F%2Ftracker.coppersurfer.tk%3A6969&amp;tr=udp%3A%2F%2Fexodus.desync.com%3A6969","seeders":1,"leechers":0,"uploader":"Lil_Jimmy1999","files":1,"time":1407857142,"description":"I Do Requests So If You Want Any Albums/Singles/ Music Videos Just Comment And I Will Upload Them For You\n\n\n\nBleachers - I Wanna Get Better\nRelease Date: March 27, 2014\nQuality: 1080p\nCover:Yes\n\nTracklist:\n01 I Wanna Get Better\n\nRequested By:dharmachatra","torrent":{"xt":"urn:btih:a6898307d2994eace9e1e2c41fff36b094ff168d","amp;dn":"Bleachers+-+I+Wanna+Get+Better+%28Mp4%29+%281080p%29+%28Lil+Jimmy%29","amp;tr":["udp%3A%2F%2Ftracker.openbittorrent.com%3A80","udp%3A%2F%2Fopen.demonii.com%3A1337","udp%3A%2F%2Ftracker.coppersurfer.tk%3A6969","udp%3A%2F%2Fexodus.desync.com%3A6969"],"infoHash":"a6898307d2994eace9e1e2c41fff36b094ff168d","infoHashBuffer":{"type":"Buffer","data":[166,137,131,7,210,153,78,172,233,225,226,196,31,255,54,176,148,255,22,141]},"announce":[],"urlList":[]}}