{"title":"Hidden Agenda Deluxe - Pan Alley Fever  2016","uid":14381483,"size":124396110,"categoryP":"audio","categoryS":"music","magnet":"?xt=urn:btih:a8b6134e0180446cf7c3eebf9f3882feb70cc1e1&amp;dn=Hidden+Agenda+Deluxe+-+Pan+Alley+Fever++2016&amp;tr=udp%3A%2F%2Ftracker.leechers-paradise.org%3A6969&amp;tr=udp%3A%2F%2Fzer0day.ch%3A1337&amp;tr=udp%3A%2F%2Fopen.demonii.com%3A1337&amp;tr=udp%3A%2F%2Ftracker.coppersurfer.tk%3A6969&amp;tr=udp%3A%2F%2Fexodus.desync.com%3A6969","seeders":1,"leechers":0,"uploader":"RoffeTheCoolMan","files":14,"time":1461233894,"description":"Hidden Agenda Deluxe – Pan Alley Fever (2016) [MP3]\r\n\r\nBand: Hidden Agenda Deluxe\r\n\r\nGenre: Country/Blues/Americana\r\nCountry: Netherlands\r\nYear: 2016\r\nAudio codec: MP3\r\nRiptype: tracks\r\nBitrate: 320 kbps\r\nPlaytime: 00:51:21\r\nSite:\nTracklist:\r\n01. Shine 03:37\r\n02. Don’t Give Up Hope 03:14\r\n03. Tulsa Shining 04:01\r\n04. Mind Of Her Own 04:23\r\n05. I Don’t Even Need You 04:03\r\n06. Don’t Forget To Leave 04:26\r\n07. Long Time Gone 05:56\r\n08. Jericho Walls 04:18\r\n09. Sweet Joanna’s Kiss 04:22\r\n10. Goodbeye Eternal Youth 04:37\r\n11. Good One Liners 02:51\r\n12. Whole 7 Days 02:25\r\n13. So Blue 03:01","torrent":{"xt":"urn:btih:a8b6134e0180446cf7c3eebf9f3882feb70cc1e1","amp;dn":"Hidden+Agenda+Deluxe+-+Pan+Alley+Fever++2016","amp;tr":["udp%3A%2F%2Ftracker.leechers-paradise.org%3A6969","udp%3A%2F%2Fzer0day.ch%3A1337","udp%3A%2F%2Fopen.demonii.com%3A1337","udp%3A%2F%2Ftracker.coppersurfer.tk%3A6969","udp%3A%2F%2Fexodus.desync.com%3A6969"],"infoHash":"a8b6134e0180446cf7c3eebf9f3882feb70cc1e1","infoHashBuffer":{"type":"Buffer","data":[168,182,19,78,1,128,68,108,247,195,238,191,159,56,130,254,183,12,193,225]},"announce":[],"urlList":[]}}