{"title":"Pornification {New 2014} XXX_Split Scenes","uid":11602603,"size":2832152553,"categoryP":"porn","categoryS":"movies","magnet":"?xt=urn:btih:b89da4bce51550b00caaf858ab23630370e82d12&amp;dn=Pornification+%7BNew+2014%7D+XXX_Split+Scenes&amp;tr=udp%3A%2F%2Ftracker.openbittorrent.com%3A80&amp;tr=udp%3A%2F%2Fopen.demonii.com%3A1337&amp;tr=udp%3A%2F%2Ftracker.coppersurfer.tk%3A6969&amp;tr=udp%3A%2F%2Fexodus.desync.com%3A6969","seeders":1,"leechers":1,"uploader":"m21wolf","files":8,"time":1417379192,"description":"Pornification {New 2014} XXX_Split Scenes\n\nStarring: \n\nDana DeArmond, AJ Applegate, Gabriella Paltrova, Marica Hase, Mr Pete, James Deen, Steve Holmes\n\nDescription: \n\nPornography Will Never Die!\n\nCover:\n &lt;a href=&quot;\nhttp://www.imgalbum.com/MA&quot; rel=&quot;nofollow&quot; target=&quot;_NEW&quot;&gt;\nhttp://www.imgalbum.com/MA&lt;/a&gt;\n &lt;a href=&quot;\nhttp://www.imgalbum.com/MD&quot; rel=&quot;nofollow&quot; target=&quot;_NEW&quot;&gt;\nhttp://www.imgalbum.com/MD&lt;/a&gt;\n\nThumbnail Screenshot:\n &lt;a href=&quot;\nhttp://www.imgalbum.com/Mu&quot; rel=&quot;nofollow&quot; target=&quot;_NEW&quot;&gt;\nhttp://www.imgalbum.com/Mu&lt;/a&gt;\n &lt;a href=&quot;\nhttp://www.imgalbum.com/M5&quot; rel=&quot;nofollow&quot; target=&quot;_NEW&quot;&gt;\nhttp://www.imgalbum.com/M5&lt;/a&gt;\n &lt;a href=&quot;\nhttp://www.imgalbum.com/M1&quot; rel=&quot;nofollow&quot; target=&quot;_NEW&quot;&gt;\nhttp://www.imgalbum.com/M1&lt;/a&gt;\n &lt;a href=&quot;\nhttp://www.imgalbum.com/Mf&quot; rel=&quot;nofollow&quot; target=&quot;_NEW&quot;&gt;\nhttp://www.imgalbum.com/Mf&lt;/a&gt;\n\nDownload, Seed &amp; Enjoy :)","torrent":{"xt":"urn:btih:b89da4bce51550b00caaf858ab23630370e82d12","amp;dn":"Pornification+%7BNew+2014%7D+XXX_Split+Scenes","amp;tr":["udp%3A%2F%2Ftracker.openbittorrent.com%3A80","udp%3A%2F%2Fopen.demonii.com%3A1337","udp%3A%2F%2Ftracker.coppersurfer.tk%3A6969","udp%3A%2F%2Fexodus.desync.com%3A6969"],"infoHash":"b89da4bce51550b00caaf858ab23630370e82d12","infoHashBuffer":{"type":"Buffer","data":[184,157,164,188,229,21,80,176,12,170,248,88,171,35,99,3,112,232,45,18]},"announce":[],"urlList":[]}}