{"title":"Roommates.S01E01.The.Roommate.HDTV.XviD-FQM","uid":4796076,"size":191425623,"categoryP":"video","categoryS":"tv_shows","magnet":"?xt=urn:btih:c07a4e7765729a81ffe9275d28eb650273fa8f01&amp;dn=Roommates.S01E01.The.Roommate.HDTV.XviD-FQM&amp;tr=udp%3A%2F%2Ftracker.openbittorrent.com%3A80&amp;tr=udp%3A%2F%2Fopen.demonii.com%3A1337&amp;tr=udp%3A%2F%2Ftracker.coppersurfer.tk%3A6969&amp;tr=udp%3A%2F%2Fexodus.desync.com%3A6969","seeders":1,"leechers":1,"uploader":"REQ-TV","files":13,"time":1237887340,"description":"Release Type: HDTV\nSeries: Roommates\nGenre: Comedy\nEpisode: S01E01\nTitle: The Roommate\nProduction Code: 101\nOrig. Air Date: 23 Mar 2009\nRelease Date: 24 Mar 2009\nSource: 720p HDTV\nVideo Format: XviD\nVideo Resolution: 624x352\nVideo Bitrate: 1055 kbps\nVideo Framerate: 23.976\nAudio Format: MP3 VBR\nAudio Bitrate: 159 kbps average\nAudio Sample Rate: 48 KHz\nLength: 19:55.361\nSize: 183,448,776\nPacks: 10*20MB = 174MB\nLink: http://abcfamily.go.com/\n\nSummary\n\nAfter graduating from college, a group of friends in New\nYork City move in together and attempt to discover more\nabout the intricate nature of the real world\n\nRelease Notes\n\nGroup Greets\n\nCTU, ORENJi, 2HD, DHD\n\nand all other groups that choose quality over speed\n\nContact Info\n\nWe are currently looking for:\n\n* US/CA cappers with HDTV and/or DSR feed - min 60 kB/s\n\nGROUP NEWS: No, we will not affil your brand new/DR/colo site\nso please don't ask. Thanks!\n\ncontact: Ask your friends. Email is dead\n\nFQM FQM\n2oo7","torrent":{"xt":"urn:btih:c07a4e7765729a81ffe9275d28eb650273fa8f01","amp;dn":"Roommates.S01E01.The.Roommate.HDTV.XviD-FQM","amp;tr":["udp%3A%2F%2Ftracker.openbittorrent.com%3A80","udp%3A%2F%2Fopen.demonii.com%3A1337","udp%3A%2F%2Ftracker.coppersurfer.tk%3A6969","udp%3A%2F%2Fexodus.desync.com%3A6969"],"infoHash":"c07a4e7765729a81ffe9275d28eb650273fa8f01","infoHashBuffer":{"type":"Buffer","data":[192,122,78,119,101,114,154,129,255,233,39,93,40,235,101,2,115,250,143,1]},"announce":[],"urlList":[]}}