{"title":"Armin Van Buuren live at Ultra 2013","uid":8277679,"size":885157049,"categoryP":"video","categoryS":"music_videos","magnet":"?xt=urn:btih:c3bff262839f9282d7786e92663b483c8135b733&amp;dn=Armin+Van+Buuren+live+at+Ultra+2013&amp;tr=udp%3A%2F%2Ftracker.openbittorrent.com%3A80&amp;tr=udp%3A%2F%2Fopen.demonii.com%3A1337&amp;tr=udp%3A%2F%2Ftracker.coppersurfer.tk%3A6969&amp;tr=udp%3A%2F%2Fexodus.desync.com%3A6969","seeders":1,"leechers":0,"uploader":"Jeffeh","files":1,"time":1363755490,"description":"Armin Van Buuren live at Ultra 2013","torrent":{"xt":"urn:btih:c3bff262839f9282d7786e92663b483c8135b733","amp;dn":"Armin+Van+Buuren+live+at+Ultra+2013","amp;tr":["udp%3A%2F%2Ftracker.openbittorrent.com%3A80","udp%3A%2F%2Fopen.demonii.com%3A1337","udp%3A%2F%2Ftracker.coppersurfer.tk%3A6969","udp%3A%2F%2Fexodus.desync.com%3A6969"],"infoHash":"c3bff262839f9282d7786e92663b483c8135b733","infoHashBuffer":{"type":"Buffer","data":[195,191,242,98,131,159,146,130,215,120,110,146,102,59,72,60,129,53,183,51]},"announce":[],"urlList":[]}}