{"title":"Body Acne Treatments.pdf","uid":4823220,"size":88083,"categoryP":"other","categoryS":"e_books","magnet":"?xt=urn:btih:c95138649d79f66a6c1b18cd1581337ea2386a1a&amp;dn=Body+Acne+Treatments.pdf&amp;tr=udp%3A%2F%2Ftracker.openbittorrent.com%3A80&amp;tr=udp%3A%2F%2Fopen.demonii.com%3A1337&amp;tr=udp%3A%2F%2Ftracker.coppersurfer.tk%3A6969&amp;tr=udp%3A%2F%2Fexodus.desync.com%3A6969","seeders":1,"leechers":0,"uploader":"sunburst77","files":1,"time":1238804288,"description":"Acne Rosacea Natural Treatment -  Does Body Acne Treatments Work\nWhat Is The Truth About Acne Vulgaris?\n\n Bacteria Destroying Concepts \n\nTo Rid You Of Lesions, Cysts, Blackheads, WhiteHeads Etc. \n\nOnce And For All","torrent":{"xt":"urn:btih:c95138649d79f66a6c1b18cd1581337ea2386a1a","amp;dn":"Body+Acne+Treatments.pdf","amp;tr":["udp%3A%2F%2Ftracker.openbittorrent.com%3A80","udp%3A%2F%2Fopen.demonii.com%3A1337","udp%3A%2F%2Ftracker.coppersurfer.tk%3A6969","udp%3A%2F%2Fexodus.desync.com%3A6969"],"infoHash":"c95138649d79f66a6c1b18cd1581337ea2386a1a","infoHashBuffer":{"type":"Buffer","data":[201,81,56,100,157,121,246,106,108,27,24,205,21,129,51,126,162,56,106,26]},"announce":[],"urlList":[]}}