{"title":"BoldlyGirls - Jessa Rhodes (Dreamy Therapy)","uid":14190252,"size":474630233,"categoryP":"porn","categoryS":"movie_clips","magnet":"?xt=urn:btih:d2df71fbdd602384170ed4528e302597f31ad407&amp;dn=BoldlyGirls+-+Jessa+Rhodes+%28Dreamy+Therapy%29++&amp;tr=udp%3A%2F%2Ftracker.leechers-paradise.org%3A6969&amp;tr=udp%3A%2F%2Fzer0day.ch%3A1337&amp;tr=udp%3A%2F%2Fopen.demonii.com%3A1337&amp;tr=udp%3A%2F%2Ftracker.coppersurfer.tk%3A6969&amp;tr=udp%3A%2F%2Fexodus.desync.com%3A6969","seeders":1,"leechers":0,"uploader":"SudoSu","files":1,"time":1459886139,"description":"http://youpornbook.com\r\n\r\n―――――――――――――――――――――――――\r\n ... : Screenshots : ... \r\n―――――――――――――――――――――――――  \nhttp://imgkiss.com/image/t5GK0 \nhttp://imgkiss.com/image/t5Oqp\r\n\r\nToday we're travelling to the fabulous LA where the famous porn actor Tommy Gunn, who just got a genital retouch surgery, will be waiting for us. Luckily for him, the beauteous Jessa Rhodes is being his private nurse and trust me, she's very good at what she does. She's so good that Tommy, helped by the medication he's taking, gets his mind into a dreamy-like phase where even their wettest sex fantasies can become a reality\r\n\r\nSail to another one:  https://thepiratebay.se/user/SudoSu/","torrent":{"xt":"urn:btih:d2df71fbdd602384170ed4528e302597f31ad407","amp;dn":"BoldlyGirls+-+Jessa+Rhodes+%28Dreamy+Therapy%29++","amp;tr":["udp%3A%2F%2Ftracker.leechers-paradise.org%3A6969","udp%3A%2F%2Fzer0day.ch%3A1337","udp%3A%2F%2Fopen.demonii.com%3A1337","udp%3A%2F%2Ftracker.coppersurfer.tk%3A6969","udp%3A%2F%2Fexodus.desync.com%3A6969"],"infoHash":"d2df71fbdd602384170ed4528e302597f31ad407","infoHashBuffer":{"type":"Buffer","data":[210,223,113,251,221,96,35,132,23,14,212,82,142,48,37,151,243,26,212,7]},"announce":[],"urlList":[]}}