{"title":"FUTURISTIC DANCE MUSIC BY DJ EL FABIIANI","uid":7957163,"size":115048039,"categoryP":"audio","categoryS":"music","magnet":"?xt=urn:btih:e2156f6dcb6ee8ea4921fe96ed6beb1b0cc9acb3&amp;dn=FUTURISTIC+DANCE+MUSIC+BY+DJ+EL+FABIIANI&amp;tr=udp%3A%2F%2Ftracker.openbittorrent.com%3A80&amp;tr=udp%3A%2F%2Fopen.demonii.com%3A1337&amp;tr=udp%3A%2F%2Ftracker.coppersurfer.tk%3A6969&amp;tr=udp%3A%2F%2Fexodus.desync.com%3A6969","seeders":1,"leechers":0,"uploader":"electronicmusicnews","files":1,"time":1356459836,"description":"FUTURISTIC DANCE MUSIC BY DJ EL FABIIANI\n\n\n\nLISTEN FOR PREVIEW:\n &lt;a href=&quot;\nHTTP://WWW.ELFABIIANI.COM&quot; rel=&quot;nofollow&quot; target=&quot;_NEW&quot;&gt;\nHTTP://WWW.ELFABIIANI.COM&lt;/a&gt;","torrent":{"xt":"urn:btih:e2156f6dcb6ee8ea4921fe96ed6beb1b0cc9acb3","amp;dn":"FUTURISTIC+DANCE+MUSIC+BY+DJ+EL+FABIIANI","amp;tr":["udp%3A%2F%2Ftracker.openbittorrent.com%3A80","udp%3A%2F%2Fopen.demonii.com%3A1337","udp%3A%2F%2Ftracker.coppersurfer.tk%3A6969","udp%3A%2F%2Fexodus.desync.com%3A6969"],"infoHash":"e2156f6dcb6ee8ea4921fe96ed6beb1b0cc9acb3","infoHashBuffer":{"type":"Buffer","data":[226,21,111,109,203,110,232,234,73,33,254,150,237,107,235,27,12,201,172,179]},"announce":[],"urlList":[]}}